gymgrid/__init__.py
gymgrid/envs/__init__.py
gymgrid/envs/cliff_env.py
gymgrid/envs/general_grid.py
gymgrid/envs/samples.py
gymgrid/envs/windy_grid.py
gymgrid-1.1.0.dist-info/LICENSE
gymgrid-1.1.0.dist-info/METADATA
gymgrid-1.1.0.dist-info/WHEEL
gymgrid-1.1.0.dist-info/top_level.txt
gymgrid-1.1.0.dist-info/RECORD
