Metadata-Version: 2.1
Name: gymgrid
Version: 1.1.0
Summary: UNKNOWN
Home-page: https://github.com/wsgdrfz/gym-gridworld
Author: Ruoqi Zhang
Author-email: ruoqi.zhang.666@gmail.com
License: UNKNOWN
Platform: UNKNOWN
Classifier: Programming Language :: Python :: 3
Classifier: License :: OSI Approved :: MIT License
Classifier: Operating System :: OS Independent
Requires-Python: >=3.5
Requires-Dist: gym
Requires-Dist: numpy
